jjlog/__init__.py
jjlog/jjlogger.py
jjlog-0.1.dist-info/LICENSE
jjlog-0.1.dist-info/METADATA
jjlog-0.1.dist-info/WHEEL
jjlog-0.1.dist-info/top_level.txt
jjlog-0.1.dist-info/RECORD
