Metadata-Version: 2.1
Name: jjlog
Version: 0.1
Summary: logger with standard/common format
Home-page: https://gitlab.com/mhliu8/jjlog
Author: John Jang
Author-email: mhliu8@gmail.com
License: MIT
Platform: UNKNOWN
Classifier: Programming Language :: Python :: 3
Classifier: License :: OSI Approved :: MIT License
Classifier: Operating System :: OS Independent
License-File: LICENSE
